{"antiFeatures":{},"apksigner":"/Users/fabi/Library/Android/sdk/build-tools/35.0.0/apksigner","archivePolicy0":[],"commandLine":["/Users/fabi/repo/soundcrowd.github.io/venv/bin/fdroid update","-v","-c","--allow-disabled-algorithms"],"disabled":[],"endTimestamp":1770499663948,"failedBuilds":{},"jarsigner":"/usr/bin/jarsigner","keytool":"/usr/bin/keytool","needsUpdate":["a89749c41461279c26e1957c2854ed8b1833920cf1ccd1239d7692ae7734262b","com.tiefensuche.soundcrowd.plugins.beatport","com.tiefensuche.soundcrowd.plugins.cache","com.tiefensuche.soundcrowd.plugins.soundcloud","com.tiefensuche.soundcrowd.plugins.spotify","com.tiefensuche.soundcrowd.plugins.tidal","com.tiefensuche.soundcrowd.plugins.youtube","com.tiefensuche.soundcrowd"],"noPackages":["a89749c41461279c26e1957c2854ed8b1833920cf1ccd1239d7692ae7734262b","com.tiefensuche.soundcrowd.plugins.beatport","com.tiefensuche.soundcrowd.plugins.cache","com.tiefensuche.soundcrowd.plugins.soundcloud","com.tiefensuche.soundcrowd.plugins.spotify","com.tiefensuche.soundcrowd.plugins.tidal","com.tiefensuche.soundcrowd.plugins.youtube","com.tiefensuche.soundcrowd"],"noUpdateCheck":["a89749c41461279c26e1957c2854ed8b1833920cf1ccd1239d7692ae7734262b","com.tiefensuche.soundcrowd.plugins.beatport","com.tiefensuche.soundcrowd.plugins.cache","com.tiefensuche.soundcrowd.plugins.soundcloud","com.tiefensuche.soundcrowd.plugins.spotify","com.tiefensuche.soundcrowd.plugins.tidal","com.tiefensuche.soundcrowd.plugins.youtube","com.tiefensuche.soundcrowd"],"stages":{"delete_disabled_builds":1770499659814,"index.make repo":1770499661013,"prepare_apps repo":1770499661007,"process_apks":1770499659814,"read_added_date_from_all_apks":1770499661006,"remove_apks":1770499661005,"scan_repo_files":1770499661004},"startTimestamp":1770496059000,"subcommand":"update"}